pybambu/__init__.py
pybambu/bambu_client.py
pybambu/bambu_cloud.py
pybambu/commands.py
pybambu/const.py
pybambu/models.py
pybambu/utils.py
pybambu-1.0.1.dist-info/METADATA
pybambu-1.0.1.dist-info/WHEEL
pybambu-1.0.1.dist-info/top_level.txt
pybambu-1.0.1.dist-info/RECORD
