Metadata-Version: 2.1
Name: pybambu
Version: 1.0.1
Summary: A python library to connect to the Bambu Lab X1C over MQTT
Home-page: https://github.com/greghesp/pybambu
Author: Greg Hesp
Author-email: greg.hesp+pybambulab@gmail.com
Classifier: Programming Language :: Python :: 3
Classifier: License :: OSI Approved :: Apache Software License
Classifier: Operating System :: OS Independent
Requires-Python: >=3.9
